{"container_type": "Author", "filled": ["basics", "publications", "indices", "counts"], "scholar_id": "Y397uBoAAAAJ", "source": "AUTHOR_PROFILE_PAGE", "name": "Xiang Li", "url_picture": "https://scholar.googleusercontent.com/citations?view_op=view_photo&user=Y397uBoAAAAJ&citpid=21", "affiliation": "Qilu University of Technology (Shandong Academy of Sciences)", "interests": ["EEG", "Affective Computing", "Time Series Mining", "Online Learning", "Anomaly Detection"], "email_domain": "@sdas.org", "citedby": 1487, "publications": {"Y397uBoAAAAJ:qjMakFHDy7sC": {"container_type": "Publication", "source": "AUTHOR_PUBLICATION_ENTRY", "bib": {"title": "Exploring EEG features in cross-subject emotion recognition", "pub_year": "2018"}, "filled": false, "author_pub_id": "Y397uBoAAAAJ:qjMakFHDy7sC", "num_citations": 327, "citedby_url": "https://scholar.google.com/scholar?oi=bibs&hl=en&cites=16997309434809846566", "cites_id": ["16997309434809846566"]}, "Y397uBoAAAAJ:9yKSN-GCB0IC": {"container_type": "Publication", "source": "AUTHOR_PUBLICATION_ENTRY", "bib": {"title": "Emotion recognition from multi-channel EEG data through convolutional recurrent neural network", "pub_year": "2016"}, "filled": false, "author_pub_id": "Y397uBoAAAAJ:9yKSN-GCB0IC", "num_citations": 299, "citedby_url": "https://scholar.google.com/scholar?oi=bibs&hl=en&cites=5925780684410636603", "cites_id": ["5925780684410636603"]}, "Y397uBoAAAAJ:lSLTfruPkqcC": {"container_type": "Publication", "source": "AUTHOR_PUBLICATION_ENTRY", "bib": {"title": "EEG based emotion recognition: A tutorial and review", "pub_year": "2022"}, "filled": false, "author_pub_id": "Y397uBoAAAAJ:lSLTfruPkqcC", "num_citations": 177, "citedby_url": "https://scholar.google.com/scholar?oi=bibs&hl=en&cites=12858936755500643586", "cites_id": ["12858936755500643586"]}, "Y397uBoAAAAJ:u-x6o8ySG0sC": {"container_type": "Publication", "source": "AUTHOR_PUBLICATION_ENTRY", "bib": {"title": "EEG based emotion identification using unsupervised deep feature learning", "pub_year": "2015"}, "filled": false, "author_pub_id": "Y397uBoAAAAJ:u-x6o8ySG0sC", "num_citations": 90, "citedby_url": "https://scholar.google.com/scholar?oi=bibs&hl=en&cites=9575733803628916020", "cites_id": ["9575733803628916020"]}, "Y397uBoAAAAJ:WF5omc3nYNoC": {"container_type": "Publication", "source": "AUTHOR_PUBLICATION_ENTRY", "bib": {"title": "A quantum-inspired multimodal sentiment analysis framework", "pub_year": "2018"}, "filled": false, "author_pub_id": "Y397uBoAAAAJ:WF5omc3nYNoC", "num_citations": 88, "citedby_url": "https://scholar.google.com/scholar?oi=bibs&hl=en&cites=6992544608803663815", "cites_id": ["6992544608803663815"]}, "Y397uBoAAAAJ:TQgYirikUcIC": {"container_type": "Publication", "source": "AUTHOR_PUBLICATION_ENTRY", "bib": {"title": "A quantum-like multimodal network framework for modeling interaction dynamics in multiparty conversational sentiment analysis", "pub_year": "2020"}, "filled": false, "author_pub_id": "Y397uBoAAAAJ:TQgYirikUcIC", "num_citations": 84, "citedby_url": "https://scholar.google.com/scholar?oi=bibs&hl=en&cites=1975735989392423521", "cites_id": ["1975735989392423521"]}, "Y397uBoAAAAJ:bEWYMUwI8FkC": {"container_type": "Publication", "source": "AUTHOR_PUBLICATION_ENTRY", "bib": {"title": "Learning interaction dynamics with an interactive LSTM for conversational sentiment analysis", "pub_year": "2021"}, "filled": false, "author_pub_id": "Y397uBoAAAAJ:bEWYMUwI8FkC", "num_citations": 81, "citedby_url": "https://scholar.google.com/scholar?oi=bibs&hl=en&cites=2351804504442663432", "cites_id": ["2351804504442663432"]}, "Y397uBoAAAAJ:M3ejUd6NZC8C": {"container_type": "Publication", "source": "AUTHOR_PUBLICATION_ENTRY", "bib": {"title": "Latent factor decoding of multi-channel EEG for emotion recognition through autoencoder-like neural networks", "pub_year": "2020"}, "filled": false, "author_pub_id": "Y397uBoAAAAJ:M3ejUd6NZC8C", "num_citations": 69, "citedby_url": "https://scholar.google.com/scholar?oi=bibs&hl=en&cites=8172188527865500913", "cites_id": ["8172188527865500913"]}, "Y397uBoAAAAJ:KlAtU1dfN6UC": {"container_type": "Publication", "source": "AUTHOR_PUBLICATION_ENTRY", "bib": {"title": "A quantum-inspired sentiment representation model for twitter sentiment analysis", "pub_year": "2019"}, "filled": false, "author_pub_id": "Y397uBoAAAAJ:KlAtU1dfN6UC", "num_citations": 61, "citedby_url": "https://scholar.google.com/scholar?oi=bibs&hl=en&cites=3285109496305983189", "cites_id": ["3285109496305983189"]}, "Y397uBoAAAAJ:LkGwnXOMwfcC": {"container_type": "Publication", "source": "AUTHOR_PUBLICATION_ENTRY", "bib": {"title": "Unsupervised sentiment analysis of twitter posts using density matrix representation", "pub_year": "2018"}, "filled": false, "author_pub_id": "Y397uBoAAAAJ:LkGwnXOMwfcC", "num_citations": 38, "citedby_url": "https://scholar.google.com/scholar?oi=bibs&hl=en&cites=10226639528628350670", "cites_id": ["10226639528628350670"]}, "Y397uBoAAAAJ:d1gkVwhDpl0C": {"container_type": "Publication", "source": "AUTHOR_PUBLICATION_ENTRY", "bib": {"title": "Deep fusion of multi-channel neurophysiological signal for emotion recognition and monitoring", "pub_year": "2017"}, "filled": false, "author_pub_id": "Y397uBoAAAAJ:d1gkVwhDpl0C", "num_citations": 31, "citedby_url": "https://scholar.google.com/scholar?oi=bibs&hl=en&cites=1474399913561601722", "cites_id": ["1474399913561601722"]}, "Y397uBoAAAAJ:iH-uZ7U-co4C": {"container_type": "Publication", "source": "AUTHOR_PUBLICATION_ENTRY", "bib": {"title": "ScenarioSA: A dyadic conversational database for interactive sentiment analysis", "pub_year": "2020"}, "filled": false, "author_pub_id": "Y397uBoAAAAJ:iH-uZ7U-co4C", "num_citations": 29, "citedby_url": "https://scholar.google.com/scholar?oi=bibs&hl=en&cites=12429707787539745978", "cites_id": ["12429707787539745978"]}, "Y397uBoAAAAJ:_kc_bZDykSQC": {"container_type": "Publication", "source": "AUTHOR_PUBLICATION_ENTRY", "bib": {"title": "Variational autoencoder based latent factor decoding of multichannel EEG for emotion recognition", "pub_year": "2019"}, "filled": false, "author_pub_id": "Y397uBoAAAAJ:_kc_bZDykSQC", "num_citations": 25, "citedby_url": "https://scholar.google.com/scholar?oi=bibs&hl=en&cites=17068971204086247559", "cites_id": ["17068971204086247559"]}, "Y397uBoAAAAJ:70eg2SAEIzsC": {"container_type": "Publication", "source": "AUTHOR_PUBLICATION_ENTRY", "bib": {"title": "Multi-task learning for jointly detecting depression and emotion", "pub_year": "2021"}, "filled": false, "author_pub_id": "Y397uBoAAAAJ:70eg2SAEIzsC", "num_citations": 20, "citedby_url": "https://scholar.google.com/scholar?oi=bibs&hl=en&cites=2349988919563566626", "cites_id": ["2349988919563566626"]}, "Y397uBoAAAAJ:J_g5lzvAfSwC": {"container_type": "Publication", "source": "AUTHOR_PUBLICATION_ENTRY", "bib": {"title": "Emotion recognition from multi-channel EEG data through a dual-pipeline graph attention network", "pub_year": "2021"}, "filled": false, "author_pub_id": "Y397uBoAAAAJ:J_g5lzvAfSwC", "num_citations": 15, "citedby_url": "https://scholar.google.com/scholar?oi=bibs&hl=en&cites=11225361254797460837", "cites_id": ["11225361254797460837"]}, "Y397uBoAAAAJ:IjCSPb-OGe4C": {"container_type": "Publication", "source": "AUTHOR_PUBLICATION_ENTRY", "bib": {"title": "Encoding physiological signals as images for affective state recognition using convolutional neural networks", "pub_year": "2016"}, "filled": false, "author_pub_id": "Y397uBoAAAAJ:IjCSPb-OGe4C", "num_citations": 11, "citedby_url": "https://scholar.google.com/scholar?oi=bibs&hl=en&cites=3845940657829604063", "cites_id": ["3845940657829604063"]}, "Y397uBoAAAAJ:2osOgNQ5qMEC": {"container_type": "Publication", "source": "AUTHOR_PUBLICATION_ENTRY", "bib": {"title": "Recognizing emotions based on multimodal neurophysiological signals", "pub_year": "2015"}, "filled": false, "author_pub_id": "Y397uBoAAAAJ:2osOgNQ5qMEC", "num_citations": 10, "citedby_url": "https://scholar.google.com/scholar?oi=bibs&hl=en&cites=15886348032268492686", "cites_id": ["15886348032268492686"]}, "Y397uBoAAAAJ:pyW8ca7W8N0C": {"container_type": "Publication", "source": "AUTHOR_PUBLICATION_ENTRY", "bib": {"title": "Multi-modal sentiment and emotion joint analysis with a deep attentive multi-task learning model", "pub_year": "2022"}, "filled": false, "author_pub_id": "Y397uBoAAAAJ:pyW8ca7W8N0C", "num_citations": 6, "citedby_url": "https://scholar.google.com/scholar?oi=bibs&hl=en&cites=13593801850147171168", "cites_id": ["13593801850147171168"]}, "Y397uBoAAAAJ:M05iB0D1s5AC": {"container_type": "Publication", "source": "AUTHOR_PUBLICATION_ENTRY", "bib": {"title": "MedSeq2Seq: A medical knowledge enriched sequence to sequence learning model for Covid-19 diagnosis", "pub_year": "2021"}, "filled": false, "author_pub_id": "Y397uBoAAAAJ:M05iB0D1s5AC", "num_citations": 6, "citedby_url": "https://scholar.google.com/scholar?oi=bibs&hl=en&cites=8910929453633409440", "cites_id": ["8910929453633409440"]}, "Y397uBoAAAAJ:UeHWp8X0CEIC": {"container_type": "Publication", "source": "AUTHOR_PUBLICATION_ENTRY", "bib": {"title": "A Sensory-Data-Hosting Oriented Scheduling Strategy on Virtual Machine", "pub_year": "2013"}, "filled": false, "author_pub_id": "Y397uBoAAAAJ:UeHWp8X0CEIC", "num_citations": 4, "citedby_url": "https://scholar.google.com/scholar?oi=bibs&hl=en&cites=4739807396833467456", "cites_id": ["4739807396833467456"]}, "Y397uBoAAAAJ:pqnbT2bcN3wC": {"container_type": "Publication", "source": "AUTHOR_PUBLICATION_ENTRY", "bib": {"title": "Real-time prediction of ocean observation data based on transformer model", "pub_year": "2021"}, "filled": false, "author_pub_id": "Y397uBoAAAAJ:pqnbT2bcN3wC", "num_citations": 3, "citedby_url": "https://scholar.google.com/scholar?oi=bibs&hl=en&cites=11903462090602028286", "cites_id": ["11903462090602028286"]}, "Y397uBoAAAAJ:zYLM7Y9cAGgC": {"container_type": "Publication", "source": "AUTHOR_PUBLICATION_ENTRY", "bib": {"title": "Does tang poetry affect human emotional state? A pilot study by EEG", "pub_year": "2017"}, "filled": false, "author_pub_id": "Y397uBoAAAAJ:zYLM7Y9cAGgC", "num_citations": 3, "citedby_url": "https://scholar.google.com/scholar?oi=bibs&hl=en&cites=8479996659165250530", "cites_id": ["8479996659165250530"]}, "Y397uBoAAAAJ:35N4QoGY0k4C": {"container_type": "Publication", "source": "AUTHOR_PUBLICATION_ENTRY", "bib": {"title": "ECNN: One online deep learning model for streaming ocean data prediction", "pub_year": "2021"}, "filled": false, "author_pub_id": "Y397uBoAAAAJ:35N4QoGY0k4C", "num_citations": 2, "citedby_url": "https://scholar.google.com/scholar?oi=bibs&hl=en&cites=1446878394006362726", "cites_id": ["1446878394006362726"]}, "Y397uBoAAAAJ:RYcK_YlVTxYC": {"container_type": "Publication", "source": "AUTHOR_PUBLICATION_ENTRY", "bib": {"title": "Supercomputer supported online deep learning techniques for high throughput EEG prediction", "pub_year": "2021"}, "filled": false, "author_pub_id": "Y397uBoAAAAJ:RYcK_YlVTxYC", "num_citations": 2, "citedby_url": "https://scholar.google.com/scholar?oi=bibs&hl=en&cites=7048539398720622592", "cites_id": ["7048539398720622592"]}, "Y397uBoAAAAJ:4TOpqqG69KYC": {"container_type": "Publication", "source": "AUTHOR_PUBLICATION_ENTRY", "bib": {"title": "A Generalized Densely Connected Encoder-Decoder Network for epithelial and stromal regions segmentation in histopathological images", "pub_year": "2019"}, "filled": false, "author_pub_id": "Y397uBoAAAAJ:4TOpqqG69KYC", "num_citations": 2, "citedby_url": "https://scholar.google.com/scholar?oi=bibs&hl=en&cites=16149433183230227879", "cites_id": ["16149433183230227879"]}, "Y397uBoAAAAJ:Zph67rFs4hoC": {"container_type": "Publication", "source": "AUTHOR_PUBLICATION_ENTRY", "bib": {"title": "Virtual machine scheduling system for multiple traffic sensor data processing applications hosting", "pub_year": "2014"}, "filled": false, "author_pub_id": "Y397uBoAAAAJ:Zph67rFs4hoC", "num_citations": 2, "citedby_url": "https://scholar.google.com/scholar?oi=bibs&hl=en&cites=3713734975224395394,12755721312999291584", "cites_id": ["3713734975224395394", "12755721312999291584"]}, "Y397uBoAAAAJ:zA6iFVUQeVQC": {"container_type": "Publication", "source": "AUTHOR_PUBLICATION_ENTRY", "bib": {"title": "An Online Incremental Learning Framework for HPC Job Power Consumption Prediction", "pub_year": "2023"}, "filled": false, "author_pub_id": "Y397uBoAAAAJ:zA6iFVUQeVQC", "num_citations": 1, "citedby_url": "https://scholar.google.com/scholar?oi=bibs&hl=en&cites=692672891698494983", "cites_id": ["692672891698494983"]}, "Y397uBoAAAAJ:rO6llkc54NcC": {"container_type": "Publication", "source": "AUTHOR_PUBLICATION_ENTRY", "bib": {"title": "Prediction of chlorophyll‐a data based on triple‐stage attention recurrent neural network", "pub_year": "2022"}, "filled": false, "author_pub_id": "Y397uBoAAAAJ:rO6llkc54NcC", "num_citations": 1, "citedby_url": "https://scholar.google.com/scholar?oi=bibs&hl=en&cites=4571418912681651719", "cites_id": ["4571418912681651719"]}, "Y397uBoAAAAJ:D03iK_w7-QYC": {"container_type": "Publication", "source": "AUTHOR_PUBLICATION_ENTRY", "bib": {"title": "A Predictive Framework for Shipborne Wind Speed Measurement Correction Based on Self-Supervised Contrastive Learning", "pub_year": "2024"}, "filled": false, "author_pub_id": "Y397uBoAAAAJ:D03iK_w7-QYC", "num_citations": 0}, "Y397uBoAAAAJ:dfsIfKJdRG4C": {"container_type": "Publication", "source": "AUTHOR_PUBLICATION_ENTRY", "bib": {"title": "A Supervised Information Enhanced Multi-Granularity Contrastive Learning Framework for EEG Based Emotion Recognition", "pub_year": "2024"}, "filled": false, "author_pub_id": "Y397uBoAAAAJ:dfsIfKJdRG4C", "num_citations": 0}, "Y397uBoAAAAJ:4OULZ7Gr8RgC": {"container_type": "Publication", "source": "AUTHOR_PUBLICATION_ENTRY", "bib": {"title": "Job2Vec: A Self-Supervised Contrastive Learning Based HPC Job Power Consumption Prediction Framework", "pub_year": "2023"}, "filled": false, "author_pub_id": "Y397uBoAAAAJ:4OULZ7Gr8RgC", "num_citations": 0}, "Y397uBoAAAAJ:u_35RYKgDlwC": {"container_type": "Publication", "source": "AUTHOR_PUBLICATION_ENTRY", "bib": {"title": "EEG based Parkinson Detection through Supervised Information Enhanced Contrastive Learning", "pub_year": "2023"}, "filled": false, "author_pub_id": "Y397uBoAAAAJ:u_35RYKgDlwC", "num_citations": 0}, "Y397uBoAAAAJ:Tyk-4Ss8FVUC": {"container_type": "Publication", "source": "AUTHOR_PUBLICATION_ENTRY", "bib": {"title": "一种面向感知数据托管的虚拟机调度策略", "pub_year": "2015"}, "filled": false, "author_pub_id": "Y397uBoAAAAJ:Tyk-4Ss8FVUC", "num_citations": 0}}, "citedby5y": 1394, "hindex": 15, "hindex5y": 15, "i10index": 17, "i10index5y": 15, "cites_per_year": {"2016": 11, "2017": 22, "2018": 55, "2019": 93, "2020": 138, "2021": 241, "2022": 298, "2023": 372, "2024": 251}, "updated": "2024-08-01 08:20:18.139790"}